MANIFEST.in
README.md
setup.py
version.cache
copter/__init__.py
copter.egg-info/PKG-INFO
copter.egg-info/SOURCES.txt
copter.egg-info/dependency_links.txt
copter.egg-info/not-zip-safe
copter.egg-info/requires.txt
copter.egg-info/top_level.txt
copter/codon_usage_tables/random.json
copter/optimizers/__init__.py
copter/optimizers/genetic_algorithm.py